mlsteam_model_sdk/cli.py
mlsteam_model_sdk/__pycache__/cli.cpython-38.pyc
mlsteam_model_sdk/commands/check.py
mlsteam_model_sdk/commands/dev.py
mlsteam_model_sdk/commands/init.py
mlsteam_model_sdk/commands/install_themisdev.py
mlsteam_model_sdk/commands/mv.py
mlsteam_model_sdk/commands/utils/install_themisdev_ubuntu.sh
mlsteam_model_sdk/core/api_client.py
mlsteam_model_sdk/core/encrypt.cpython-36m-x86_64-linux-gnu.so
mlsteam_model_sdk/core/envs.py
mlsteam_model_sdk/core/exceptions.py
mlsteam_model_sdk/core/registry.py
mlsteam_model_sdk/core/version.py
mlsteam_model_sdk/core/dev/archive.py
mlsteam_model_sdk/core/dev/manifest.py
mlsteam_model_sdk/core/mlarchive_manifest_schema/v2023.1.json
mlsteam_model_sdk/core/mlarchive_manifest_schema/v2024.1.json
mlsteam_model_sdk/sdk/__init__.py
mlsteam_model_sdk/sdk/model.cpython-36m-x86_64-linux-gnu.so
mlsteam_model_sdk/sdk/helper/__init__.py
mlsteam_model_sdk/sdk/helper/loader/__init__.py
mlsteam_model_sdk/sdk/helper/loader/torch.py
mlsteam_model_sdk/sdk/helper/patch/__init__.py
mlsteam_model_sdk/sdk/helper/patch/zipfile.py
mlsteam_model_sdk/sdk/helper/predictor/__init__.py
mlsteam_model_sdk/sdk/helper/predictor/torch.py
mlsteam_model_sdk/utils/config.py
mlsteam_model_sdk/utils/db.py
mlsteam_model_sdk/utils/identity.py
mlsteam_model_sdk/utils/license.cpython-36m-x86_64-linux-gnu.so
mlsteam_model_sdk/utils/log.py
mlsteam_model_sdk/utils/my_typing.py
mlsteam_model_sdk-0.7.0.dist-info/LICENSE
mlsteam_model_sdk-0.7.0.dist-info/METADATA
mlsteam_model_sdk-0.7.0.dist-info/PSF_LICENSE_AGREEMENT_Python_3.8.txt
mlsteam_model_sdk-0.7.0.dist-info/WHEEL
mlsteam_model_sdk-0.7.0.dist-info/entry_points.txt
mlsteam_model_sdk-0.7.0.dist-info/top_level.txt
mlsteam_model_sdk-0.7.0.dist-info/RECORD
