Metadata-Version: 2.1
Name: mlsteam-model-sdk
Version: 0.7.0
Summary: MLSteam Model SDK
License: MIT
Project-URL: Homepage, https://mlsteam-model-sdk-doc.readthedocs.io/
Keywords: sdk
Classifier: Environment :: Console
Classifier: Intended Audience :: Developers
Classifier: Intended Audience :: Science/Research
Classifier: License :: OSI Approved :: MIT License
Classifier: Operating System :: POSIX :: Linux
Classifier: Programming Language :: Python
Classifier: Programming Language :: Python :: 3
Classifier: Programming Language :: Python :: Implementation :: CPython
Classifier: Topic :: Scientific/Engineering :: Artificial Intelligence
Classifier: Topic :: Software Development :: Libraries :: Python Modules
Requires-Python: >=3.6
License-File: LICENSE
License-File: PSF_LICENSE_AGREEMENT_Python_3.8.txt
Requires-Dist: bravado
Requires-Dist: click
Requires-Dist: jsonschema
Requires-Dist: psutil
Requires-Dist: pythemis
Requires-Dist: texttable
Requires-Dist: typing-extensions
Requires-Dist: dataclasses ; python_version < "3.7"
Requires-Dist: swagger-spec-validator <3.0.0 ; python_version < "3.8"
Provides-Extra: dev
Requires-Dist: bump2version ; extra == 'dev'
Requires-Dist: cython ; extra == 'dev'
Requires-Dist: george-walrus ; extra == 'dev'
Requires-Dist: mypy ; extra == 'dev'
Requires-Dist: myst-nb ; extra == 'dev'
Requires-Dist: myst-parser ~=0.18.0 ; extra == 'dev'
Requires-Dist: pytest ; extra == 'dev'
Requires-Dist: sphinx ; extra == 'dev'
Requires-Dist: sphinx-rtd-theme ; extra == 'dev'
Requires-Dist: twine ; extra == 'dev'
